Workbook

Sheet 採点表（仮採点・理由）
A1: 提案評価 採点シート｜SSBJ対応 要求定義支援ファーム選定（書面ベースの仮採点）
A2: ※本シートは提案書（書面）のみに基づく仮採点。採点ルール「書面評価は仮採点とし、コンペ質疑の回答を反映した確定素点のみ本シートに記入」に従い、黄色セル（質疑確認事項を含む項目）はコンペ質疑後に見直しのこと。得点＝配点×素点÷5（小数第1位）。裏付け（実名・事例・数値）のない主張は素点3を上限として採点。
A3: No. | B3: 採点項目 | C3: 評価の着眼点 | D3: 配点 | E3: A社：ライズ・コンサルティング | H3: B社：PwCコンサルティング | K3: C社：アビームコンサルティング
E4: 素点 | F4: 得点 | G4: 評価理由（仮採点の根拠・質疑確認事項） | H4: 素点 | I4: 得点 | J4: 評価理由（仮採点の根拠・質疑確認事項） | K4: 素点 | L4: 得点 | M4: 評価理由（仮採点の根拠・質疑確認事項）
A5: Q｜Quality（品質）— 提案内容と体制の質 | D5: 50
A6: Q1 | B6: 課題理解・前提の的確性 | C6: 戦略とシステムの並行推進・手戻り許容の特殊前提と「5つの難所」を提案全体に反映しているか | D6: 6 | E6: 4 | F6: =ROUND($D6*E6/5,1) -> 4.8 | G6: 5つの難所を提案の骨格（課題認識→アプローチ→成果物）に一貫して使用。難所1・5の先行検討と「条件付き要件」で戦略並行・手戻り許容の特殊前提に対応しており、要求を満たし先回りもある。 | H6: 4 | I6: =ROUND($D6*H6/5,1) -> 4.8 | J6: 5つの難所に独自の難所⑥（複数WSの変更連鎖管理）⑦（全世界拠点への定着）を追加し2029年開示から逆算のロードマップを提示（独自知見）。一方で標準線表がRFP発出12月末（仮）となっており、11月末RFP完了という貴社の時間軸理解にズレ。 | K6: 5 | L6: =ROUND($D6*K6/5,1) -> 6 | M6: 「戦略確定を待てない環境でのアジャイル型要件定義」「2028年1月本番収集からの逆算」と特殊前提を明文化。Cat11が主戦場・すすぎ回数等の使用条件シナリオまで貴社固有の事業構造を反映し、難所別に「落とし穴と回避策＋貴社の予防アクション」まで提示。想定超の理解度。
A7: Q2 | B7: アジャイル型要件定義の方法論 | C7: 戦略変更時に「変えない骨格／作り直す部分」を切り分ける設計手順とFit&Gapの進め方が具体的か | D7: 10 | E7: 3 | F7: =ROUND($D7*E7/5,1) -> 6 | G7: 「凍結要件／条件付き要件」の二分法と、条件付き要件の追加整理5項目（基本案・想定シナリオ・変動範囲・決定者と期限・影響範囲）は手順として具体的。ただし本方法論の適用実績（社名・事例・数値）の裏付けがなく、ルール上素点3が上限。質疑で適用事例を確認したい。 | H7: 3 | I7: =ROUND($D7*H7/5,1) -> 6 | J7: 検討事項・論点リスト（9頁分）は網羅的だが、「変えない骨格／作り直す部分」を切り分ける設計手順やFit&Gapの進め方の明示なし。ルール策定・ロジックは「貴社にて策定済み想定」と前提を置いており、戦略変更時の手戻り吸収の設計が提案上弱い。 | K7: 5 | L7: =ROUND($D7*K7/5,1) -> 10 | M7: 「戦略依存×Must/Should/Could」の2軸4象限で確定順序を設計し、変えない骨格（組織マスタ・証憑統制・Scope1/2算定等）と「共通要件＋重要テーマ別シナリオ」の二層整理を具体的な機能レベルまで例示。時価総額3兆・1兆円企業で開示・保証要件未確定下の適用実績を裏付けとして提示。
A8: Q3 | B8: 守りの設計力（統制・証跡・自動化） | C8: 証憑紐付け・多段階承認・変更履歴保全を機能要件へ落とす道筋と、手作業根絶のプロセス設計が具体的か | D8: 8 | E8: 3 | F8: =ROUND($D8*E8/5,1) -> 4.8 | G8: 証憑紐付け要件定義・版管理・変更管理方針書等、成果物への道筋は示されるが記載は一般論の域。手作業根絶のプロセス設計の具体度と実績の裏付けが薄い。 | H8: 5 | I8: =ROUND($D8*H8/5,1) -> 8 | J8: 統制要素×確認領域のマトリクス、「人による確認・判断」と「システムによる保持・追跡」の分担、請求書按分・単位変換・例外処理の証跡定義まで、機能要件へ落とす道筋が3社中最も具体的。監査法人（PwCあらた）との連携体制と全世界500拠点の統制構築実績が裏付け。 | K8: 5 | L8: =ROUND($D8*K8/5,1) -> 8 | M8: 公認会計士（元大手監査法人パートナー・保証15年）を体制に配置し、キーコントロール定義・非財務決算プロセス統制・保証人指摘対応を実際の作成物レベルで提示。「過剰にしない統制」の設計思想と保証人の早期巻き込みによる「後出しNG」予防まで具体的。
A9: Q4 | B9: 攻めの設計力（非財務の財務化） | C9: Scope3一次データ化・CFP即応・AI将来予測をPBR向上・受注拡大へ接続する定量ストーリーがあるか | D9: 8 | E9: 3 | F9: =ROUND($D9*E9/5,1) -> 4.8 | G9: 可視化・活用の初期仮説（意思決定起点のKPI設計・多目的出力）はあるが、PBR向上・受注拡大へ接続する定量ストーリーはなし。一般論の範囲。 | H9: 4 | I9: =ROUND($D9*H9/5,1) -> 6.4 | J9: Step1〜3の企業価値向上ステップに加え、残余利益モデルによる非財務属性×資本コスト・理論株価の定量分析方法論（Appendix）は独自性あり。ただし将来予測・サプライヤー連携（Scope3一次データ化）を「Step2以降」とし、本フェーズの要件化からは外している。 | K9: 4 | L9: =ROUND($D9*K9/5,1) -> 6.4 | M9: 攻めユースケース6件を効果×実現性で事前評価（CFP即応＝受注シェア直結、削減貢献量＝Cat11の価値訴求・IR直結等）し、2〜3件への絞り込みと基盤要件化までをスコープに内蔵。Digital ESG方法論（非財務資本投下×企業価値の関係分析）を鉄道・不動産・通信・建設等で適用した実績。定量成果の実例までは未提示のため4。
A10: Q5 | B10: 実績・知見（SSBJ／保証／類似基盤） | C10: 類似案件の実績を「社名・時期・自社の役割・定量成果」の4点セットで示し、失敗と回避策を語れるか | D10: 10 | E10: 2 | F10: =ROUND($D10*E10/5,1) -> 4 | G10: 会社としてのSSBJ／保証／類似基盤の実績が「社名・時期・役割・定量成果」の4点セットで示されず、個人経歴（官公庁の要件定義・ベンダー選定等）への依存。SSBJ固有の会社実績が書面で確認できない。 | H10: 4 | I10: =ROUND($D10*H10/5,1) -> 8 | J10: Net Zero Cloud／Workiva等の導入実績多数。全世界500拠点・国内サプライヤー300社・700拠点等の定量規模、公表事例（日経BP記事）、Net Zero Cloud Partner of the Year受賞。ただし多くが業種表記（社名非開示）で時期の明示も乏しく、4点セットとしては不完全。 | K10: 5 | L10: =ROUND($D10*K10/5,1) -> 10 | M10: SGホールディングス（実名・2026年7月プレスリリース公表済み）、時価総額3兆円企業へのSSBJ支援を明示。業界別事例に期間（3／5／7ヶ月）と定量成果（GRESB 3→4スター、RFP4社発出→選定完了）を付し、難所別に「避けるべき参考事例（失敗）と回避策」を語っており、4点セットに最も近い。
A11: Q6 | B11: 投入メンバーの専門性（実名） | C11: 実名・経歴・類似案件経験が提示され、従事予定者本人がコンペに出席し自らの言葉で語れるか | D11: 8 | E11: 3 | F11: =ROUND($D11*E11/5,1) -> 4.8 | G11: 実名提示はあるがPM「田村 or 豊田」、リード「大谷 or 白石」と主要2ポジションが未確定。メンバーは「受注後迅速に決定」。SME中村氏の専門性は高い。本人のコンペ出席と確定を質疑で要確認。 | H11: 2 | I11: =ROUND($D11*H11/5,1) -> 3.2 | J11: リード小林P（関与5%）・PM須貝SM（20%）は実名・経歴・実績が詳細。ただし100%稼働の実働3名（SA/A）が全員TBDで実名・経歴なし。成果物品質の大半を担う層が匿名であり、書面では実現性を判断できない。 | K11: 4 | L11: =ROUND($D11*K11/5,1) -> 6.4 | M11: 主要6名を実名・経歴・類似実績付きで提示（PM山野氏＝食品メーカーのSSBJ報告プロセス可視化・内部統制整備、張本氏＝公認会計士15年）。ただし実働コンサルタント3名はTBD、「参画メンバーは変更になる可能性」の注記あり。本人出席と交代条件を質疑で要確認。
A12: Q 小計 | D12: =SUM(D6:D11) -> 50 | F12: =ROUND(SUM(F6:F11),1) -> 29.2 | I12: =ROUND(SUM(I6:I11),1) -> 36.4 | L12: =ROUND(SUM(L6:L11),1) -> 46.8
A13: C｜Cost（コスト）— 価格の妥当性と統制 | D13: 23
A14: C1 | B14: 見積総額の妥当性 | C14: 3ヶ月スコープ・成果物10点に対し市場相場・投入体制と整合するか（極端な安値は実態確認のうえ減点） | D14: 6 | E14: 3 | F14: =ROUND($D14*E14/5,1) -> 3.6 | G14: 値引後2,400万円（税抜）は3ヶ月・実働4〜5名として相場下限。定価3,520万円からの32%値引き（▲1,120万円）は採点ルール上「極端な安値」の確認対象。値引きの持続性（次フェーズ単価）と体制維持の実態を質疑で確認のうえ確定。 | H14: 4 | I14: =ROUND($D14*H14/5,1) -> 4.8 | J14: 案①3,350万／案②2,700万／案③2,150万円と3案でスコープと金額の対応が開示され、体制との整合も説明可能。3ヶ月強・実働3名＋管理として市場相場レンジ内。 | K14: 2 | L14: =ROUND($D14*K14/5,1) -> 2.4 | M14: 7,800万円（税抜）は他社比2.3〜3.6倍。期間5ヶ月・ベンダー評価／非システム課題／効果試算までのスコープ拡張が要因だが、貴社が定義した「3ヶ月・成果物10点」に対応する金額が切り出されておらず、書面では妥当性を検証できない。基準スコープの切り出し見積りを質疑で要求。
A15: C2 | B15: 工数・単価の透明性 | C15: ランク別単価×人数×稼働率×期間の内訳が開示され、WBSのタスクと工数の対応を検証できるか | D15: 6 | E15: 2 | F15: =ROUND($D15*E15/5,1) -> 2.4 | G15: 内訳非開示（総額＋値引き額のみ）。体制表にフルタイム／パートタイムの区分はあるが、ランク別単価・稼働率%・工数がなく、WBS別紙とタスク工数の対応も検証不可。 | H15: 3 | I15: =ROUND($D15*H15/5,1) -> 3.6 | J15: メンバー別・月別の関与工数%を唯一開示（P5%・SM20%・実働100%×3名等）。ただしランク別単価は非開示のため、単価×工数の妥当性検証まではできない。 | K15: 2 | L15: =ROUND($D15*K15/5,1) -> 2.4 | M15: 総額のみで単価・工数・稼働率の内訳なし。タスク一覧（15タスク）は3社中最も詳細だが、タスクと工数・金額の対応が示されていない。
A16: C3 | B16: 追加費用条件・変更管理 | C16: 手戻り・スコープ変更時の費用発生条件と変更管理手続きが契約前に明文化されているか | D16: 5 | E16: 2 | F16: =ROUND($D16*E16/5,1) -> 2 | G16: 「その他諸費用が発生する場合は相談の上別途請求」のみ。手戻り・スコープ変更時の費用発生条件、変更管理手続きの明文化なし。 | H16: 3 | I16: =ROUND($D16*H16/5,1) -> 3 | J16: 「作業範囲・作業量の大幅な拡大・増加により当初見積り超過の可能性が生じた場合は、速やかに相談のうえ再見積り」と契約前に明文化。変更管理の承認手続きまでは未定義。 | K16: 3 | L16: =ROUND($D16*K16/5,1) -> 3 | M16: 「期間・業務内容・前提条件が変更となる場合は相談のうえ改めて提案」を明文化。加えて「ベンダー評価は1月末までに回答があった企業に限る」等、対応範囲の条件を明示している。
A17: C4 | B17: 費用対効果の説明力 | C17: 支援により回避できるコスト（監査工数・手戻り・ベンダー選定失敗）と投資額の関係を説明できるか | D17: 6 | E17: 3 | F17: =ROUND($D17*E17/5,1) -> 3.6 | G17: 監査コスト増・開示遅延・品質低下等の経営リスクは定性的に説明されるが、回避コストと投資額の定量的な関係の説明なし。 | H17: 3 | I17: =ROUND($D17*H17/5,1) -> 3.6 | J17: 保証工数削減による開示リードタイム短縮、業務工数削減への言及はあるが、回避コストと投資額の定量関係の説明はなし。 | K17: 4 | L17: =ROUND($D17*K17/5,1) -> 4.8 | M17: 「工数削減額・リスク回避額・収益機会」の効果3分類で投資をリターンに転換するコンセプトを掲げ、As-Is実測に基づくROI精緻化・経営上申資料の作成をタスク（#15）としてスコープに内蔵。定量の実例までは未提示のため4。
A18: C 小計 | D18: =SUM(D14:D17) -> 23 | F18: =ROUND(SUM(F14:F17),1) -> 11.6 | I18: =ROUND(SUM(I14:I17),1) -> 15 | L18: =ROUND(SUM(L14:L17),1) -> 12.6
A19: D｜Delivery（納期）— 3ヶ月完遂の確実性 | D19: 27
A20: D1 | B20: 実行計画（WBS）の実現性 | C20: 9〜11月の計画に海外拠点ヒアリング統合等の依存関係とクリティカルパスが織り込まれているか | D20: 8 | E20: 3 | F20: =ROUND($D20*E20/5,1) -> 4.8 | G20: 9〜11月の週次線表とWBS別紙（案)を提示。ただし海外拠点ヒアリング（9月末回収）等の外部依存の統合やクリティカルパスの明示が確認できない。 | H20: 2 | I20: =ROUND($D20*H20/5,1) -> 3.2 | J20: 週単位の詳細線表と海外拠点ヒアリング結果の取込みを明示。ただし計画期間が9/7〜12/25でRFP発出12月末（仮）となっており、「9〜11月」の3ヶ月完遂計画として成立していない。 | K20: 4 | L20: =ROUND($D20*K20/5,1) -> 6.4 | M20: 2028年1月本番収集からの逆線表、9月末海外拠点ヒアリング完了のマイルストーン化、候補ベンダーのリスト化・応札意思打診の前倒し等、依存関係とクリティカルパスの織り込みは3社中最も明確。ただし全体は5ヶ月計画であり11月末に収まっていない。
A21: D2 | B21: 成果物完遂のコミット | C21: 11月末までの「システムRFP一式の発行完了」を含む成果物10点の完遂を工程表つきで確約しているか | D21: 8 | E21: 4 | F21: =ROUND($D21*E21/5,1) -> 6.4 | G21: 「11月末時点で作成した成果物に対して貴社承認済み」「次工程で発出するRFPの作成が完了」と完了状態を定義し工程表を提示。唯一11月末要求に整合。ただし成果物構成（要件定義書3点＋RFP本紙＋評価要領）と貴社想定成果物10点との対応が粗く、対応表を質疑で要確認。 | H21: 2 | I21: =ROUND($D21*H21/5,1) -> 3.2 | J21: 成果物マッピング表は3社中最も丁寧（貴社想定より多い成果物を提示）。ただしRFP発出は12月末（仮）であり、11月末までの「RFP一式の発行完了」の確約なし。 | K21: 2 | L21: =ROUND($D21*K21/5,1) -> 3.2 | M21: 要件定義完了12月中旬・RFP発行「年内」であり、11月末の確約なし。ベンダー評価（1月末）まで含む充実したスコープだが、貴社マイルストーンとは約1ヶ月のズレ。前倒し可否を質疑で要確認。
A22: D3 | B22: 体制の稼働率・継続性 | C22: 主要メンバーの稼働率（％）明示、期間中の交代禁止または交代時の品質担保条件、他案件重複の開示 | D22: 6 | E22: 2 | F22: =ROUND($D22*E22/5,1) -> 2.4 | G22: フルタイム／パートタイム表記のみで稼働率%の明示なし。交代禁止・交代時の品質担保条件なし。主要ポジションの「or」表記も継続性上の懸念。 | H22: 3 | I22: =ROUND($D22*H22/5,1) -> 3.6 | J22: 稼働率%を唯一、メンバー別・月別に明示（要求水準に合致）。ただし交代禁止・品質担保条件の記載がなく、100%稼働の3名がTBDである点が減点。 | K22: 2 | L22: =ROUND($D22*K22/5,1) -> 2.4 | M22: 稼働率%の明示なし。「実際の人数はタスクに応じて調整」「参画メンバーは変更になる可能性があります」との注記があり、交代禁止・継続性のコミットが書面上ない。
A23: D4 | B23: 遅延リスク管理・手戻り対応 | C23: 両輪並行に伴う手戻りの吸収策（バッファ・優先順位ルール・早期警報の仕組み）が計画に組み込まれているか | D23: 5 | E23: 4 | F23: =ROUND($D23*E23/5,1) -> 4 | G23: リスク一覧（発生可能性・顕在化防止策・顕在化時対応）を明示。「条件付き要件」により要件未確定でもRFPへ進める手戻り吸収策が計画に内蔵されており、両輪並行の前提に整合。 | H23: 3 | I23: =ROUND($D23*H23/5,1) -> 3 | J23: 難所⑥として変更連鎖管理を指摘し全体マネジメント機能を設置。ただしバッファ・優先順位ルール・早期警報といった具体的な仕組みの記載はなし。 | K23: 4 | L23: =ROUND($D23*K23/5,1) -> 4 | M23: 遅延時リカバリ方針の事前合意、マイルストーン・KPIモニタリング、選定期間圧縮（応札意思の事前打診・ドラフトRFP先行共有）、督促自動化、保証人早期巻き込みによる後出し防止等、遅延・手戻りの予防策が計画に組み込まれている。
A24: D 小計 | D24: =SUM(D20:D23) -> 27 | F24: =ROUND(SUM(F20:F23),1) -> 17.6 | I24: =ROUND(SUM(I20:I23),1) -> 13 | L24: =ROUND(SUM(L20:L23),1) -> 16
A25: 合計（Q50＋C23＋D27） | D25: 100 | F25: =ROUND(F12+F18+F24,1) -> 58.4 | I25: =ROUND(I12+I18+I24,1) -> 64.4 | L25: =ROUND(L12+L18+L24,1) -> 75.4

Sheet サマリ
A1: 採点結果サマリ（書面ベース仮採点）
A3: 区分 | B3: 配点 | C3: A社：ライズ | D3: B社：PwC | E3: C社：アビーム
A4: Q：品質 | B4: 50 | C4: ='採点表（仮採点・理由）'!F12 -> 29.2 | D4: ='採点表（仮採点・理由）'!I12 -> 36.4 | E4: ='採点表（仮採点・理由）'!L12 -> 46.8
A5: C：コスト | B5: 23 | C5: ='採点表（仮採点・理由）'!F18 -> 11.6 | D5: ='採点表（仮採点・理由）'!I18 -> 15 | E5: ='採点表（仮採点・理由）'!L18 -> 12.6
A6: D：納期 | B6: 27 | C6: ='採点表（仮採点・理由）'!F24 -> 17.6 | D6: ='採点表（仮採点・理由）'!I24 -> 13 | E6: ='採点表（仮採点・理由）'!L24 -> 16
A7: 合計 | B7: 100 | C7: ='採点表（仮採点・理由）'!F25 -> 58.4 | D7: ='採点表（仮採点・理由）'!I25 -> 64.4 | E7: ='採点表（仮採点・理由）'!L25 -> 75.4
A10: 【総評（書面ベース）】
A11: ■ C社アビーム：品質（Q）が突出。貴社固有の前提（Cat11・戦略並行・2028/1逆算）の理解、アジャイル方法論、実名実績（SGホールディングス等）、公認会計士配置が強み。
A12: 一方、7,800万円は「3ヶ月・成果物10点」の基準スコープ外（ベンダー評価・非システム課題・効果試算・5ヶ月）を含み、切り出し見積りなしでは価格妥当性を検証できない。RFP発行も「年内」で11月末未達。
A13: ■ B社PwC：守りの設計力（統制・証跡）と導入実績の定量規模はトップ級。3案提示・稼働率%開示など透明性は最良。
A14: 致命的な懸念は①実働3名（100%稼働）が全員TBD＝品質の担い手が不明、②RFP発出12月末（仮）＝11月末要求と不整合、の2点。質疑での解消が採用の前提条件。
A15: ■ A社ライズ：唯一11月末RFP完成にコミットし価格も最安（値引後2,400万円）。「条件付き要件」の方法論は本件の特殊前提に整合。
A16: ただしSSBJ固有の会社実績が4点セットで示されず、主要メンバーが「or」表記で未確定、32%値引きは安値の実態確認（体制・品質の維持可否）が必要。
A18: 【コンペ質疑での必須確認事項】
A19: ・全社共通：貴社想定成果物10点との対応表／「11月末RFP発行完了」の達成可否と前提／ランク別単価×稼働率×期間の内訳（統一フォーマット）
A20: ・A社：値引きの持続性（次フェーズ単価）／PM・リードの確定と本人出席／SSBJ類似案件の会社実績
A21: ・B社：実働3名の実名・経歴の提示／11月末完了へ前倒しした場合の体制・金額／交代時の品質担保条件
A22: ・C社：基準スコープ（3ヶ月・RFP作成まで）の切り出し金額／11月末前倒しの可否／稼働率%と交代条件の明示

Sheet 金額差分析
A1: 金額差の要因分析とApple to Apple化の方法
A3: 比較項目 | B3: A社：ライズ | C3: B社：PwC | D3: C社：アビーム | E3: 備考
A4: 提示金額（税抜） | B4: 2,400万円 （定価3,520万円、値引▲1,120万円） | C4: 案① 3,350万円 案② 2,700万円 案③ 2,150万円 | D4: 7,800万円 | E4: スコープが各社異なるため、この金額の直接比較は不可
A5: 支援期間 | B5: 9/1〜11/30（3.0ヶ月） | C5: 9/7〜12/25（約3.6ヶ月） | D5: 9/1〜1/31（5.0ヶ月） | E5: 貴社要求は9〜11月の3ヶ月
A6: 月額換算（概算） | B6: 約800万円/月 | C6: 案①約930万円/月 案②約750万円/月 | D6: 約1,560万円/月 | E6: 期間差を除いた粗い比較。体制規模の差を含む
A7: RFP完成・発行時期 | B7: 11月末に作成完了・貴社承認済み（発出は後続） | C7: RFP発出 12月末（仮） | D7: RFP発行 年内（12月） | E7: 11月末要求を満たすのはA社のみ
A8: ベンダー評価・選定 | B8: 含まない（後続フェーズ） | C8: 含まない | D8: 含む（2027年1月末まで） | E8: C社の金額を押し上げる主要因①
A9: 非システム課題の整理・ロードマップ（ガバナンス・内部統制・サステナマネジメント） | B9: 含まない | C9: 含まない | D9: 含む | E9: C社の金額を押し上げる主要因②
A10: 効果試算・ROI・経営上申支援 | B10: 含まない | C10: 含まない（Appendixに方法論提示のみ） | D10: 含む（As-Is実測ベースのROI精緻化・上申資料） | E10: C社の金額を押し上げる主要因③
A11: 展開計画・定着計画・PJ計画書 | B11: 含まない | C11: 案①②は含む（案③は含まない） | D11: 一部含む（システム化方針書） | E11: B社の案①②③の価格差の主要因
A12: アーキテクチャ検討 | B12: 非機能要件の一部として整理 | C12: 案①②は素案作成を含む | D12: システム構成案策定を含む
A13: 攻め（経営活用）の要件化 | B13: 初期仮説の提示まで | C13: Step2以降に後ろ倒し | D13: ユースケース2〜3件の絞り込み・基盤要件化まで含む | E13: スコープの深さの差
A14: 実働体制 | B14: フルタイム2名＋パートタイム2名＋SME適宜 （主要2ポジションが「or」表記） | C14: SA/A 3名（100%）＋SM20%＋P5% （実働3名はTBD） | D14: M＋SC＋コンサル3名＋アドバイザー4名（P/D/SM級、公認会計士含む） | E14: C社は管理・専門層が厚い＝金額を押し上げる主要因④
A15: ファームの単価水準 | B15: 中堅独立系（相対的に低単価） | C15: Big4（高単価だが実働はジュニア層） | D15: 大手総合（高単価、シニア層厚め） | E15: 同ランクでも月単価に1.5〜2倍の開きが生じ得る
A16: 値引き | B16: ▲1,120万円（32%：初回値引＋出精値引） | C16: なし | D16: なし | E16: A社の安さの一部は戦略価格。次フェーズ単価の確認が必要
A18: 【金額差の構造（要約）】
A19: 金額差＝①期間の差（3.0〜5.0ヶ月：最大1.67倍）×②スコープの差（C社のみベンダー評価・非システム課題・効果試算を含む／B社は案により展開計画等が増減）×③体制の厚み（C社はシニア・専門家層が厚い、B社は実働がジュニア3名）×④ファーム単価水準（Big4・大手総合＞中堅独立系）×⑤値引き（A社▲32%）。
A20: 粗い試算：C社から「ベンダー評価＋非システム課題＋効果試算＋12〜1月分」を除き3ヶ月相当に換算すると概ね4,500〜5,500万円規模と推定され、それでも残る対A社・B社との差は主に体制の厚みと単価水準の差。
A22: 【Apple to Apple化のための5つのアクション（質疑・再見積り依頼時）】
A23: ① 基準スコープの固定 | B23: 「9〜11月・貴社想定成果物10点・11月末RFP発行可能状態」を基準スコープと定義し、(a)基準スコープの金額と(b)オプション（ベンダー評価支援／非システム課題整理／効果試算／展開・定着計画／アーキテクチャ素案）を分離した再見積りを3社に要求する。C社にはベンダー評価等の切り出し、B社には案②ベースで11月末前倒し時の金額、A社には成果物10点との対応表と不足分（海外拠点拡張ロードマップ等）込みの金額を求める。
A24: ② 工数・単価の統一フォーマット | B24: ランク別単価×人数×稼働率（%）×期間のマトリクスと、WBSタスクとの工数対応表を統一様式で提出させる（採点項目C2の確定にも直結）。
A25: ③ 前提条件の統一 | B25: As-Is成果物の受領範囲／海外拠点ヒアリング（9月末回収）の役割分担／貴社側意思決定のリードタイム／経費の扱い（3社とも実費別途→上限設定）／見積有効期限（B社・C社は8月末）を統一条件として明示する。
A26: ④ 値引きの正規化 | B26: A社は定価（3,520万円）ベースでも比較し、値引きの適用条件と次フェーズ以降の単価水準を確認する（採点ルール上の「極端な安値の実態確認」に該当）。
A27: ⑤ 体制の確定 | B27: 実名・稼働率%・期間中の交代禁止（または交代時の品質担保条件）・他案件との重複状況を統一様式で提出させる（A社の「or」、B社の実働TBD、C社の「変更の可能性」注記をすべて解消してから価格を比較する）。
